ny_lektion/__init__.py
ny_lektion/ny_lektion.py
ny_lektion-1.0.0.dist-info/licenses/LICENSE
ny_lektion-1.0.0.dist-info/METADATA
ny_lektion-1.0.0.dist-info/WHEEL
ny_lektion-1.0.0.dist-info/entry_points.txt
ny_lektion-1.0.0.dist-info/top_level.txt
ny_lektion-1.0.0.dist-info/RECORD
