Metadata-Version: 2.4
Name: ny_lektion
Version: 1.0.0
Summary: A simple CLI tool to scaffold new lektion projects
Author: Sam Parsakian
Requires-Python: >=3.7
License-File: LICENSE
Dynamic: author
Dynamic: description
Dynamic: description-content-type
Dynamic: license-file
Dynamic: requires-python
Dynamic: summary
